aihub/__init__.py
aihub/aihub.py
aihub/api_client.py
aihub/api_response.py
aihub/configuration.py
aihub/exceptions.py
aihub/py.typed
aihub/rest.py
aihub/api/__init__.py
aihub/api/audit_api.py
aihub/api/batches_api.py
aihub/api/conversations_api.py
aihub/api/files_api.py
aihub/api/jobs_api.py
aihub/api/queries_api.py
aihub/api/runs_api.py
aihub/api/secrets_api.py
aihub/models/__init__.py
aihub/models/batch.py
aihub/models/batch_deletion_job_response.py
aihub/models/batch_info.py
aihub/models/bounding_box.py
aihub/models/case_info.py
aihub/models/case_info_field.py
aihub/models/case_input_field.py
aihub/models/commit_multipart_upload_session_request.py
aihub/models/commit_multipart_upload_session_request_parts_inner.py
aihub/models/conversation.py
aihub/models/conversation_response.py
aihub/models/conversation_response_upload_status.py
aihub/models/conversation_response_upload_status_failure_inner.py
aihub/models/conversation_response_upload_status_success_inner.py
aihub/models/conversation_summary.py
aihub/models/converse_request.py
aihub/models/create_batch_request.py
aihub/models/create_multipart_upload_session_request.py
aihub/models/create_secret_request.py
aihub/models/delete_documents_from_conversation_request.py
aihub/models/delete_run202_response.py
aihub/models/delete_secret_request.py
aihub/models/deployment_run.py
aihub/models/document.py
aihub/models/document_classification_confidence.py
aihub/models/document_details.py
aihub/models/document_field.py
aihub/models/document_field_confidence.py
aihub/models/document_field_validations.py
aihub/models/document_field_validations_alerts_inner.py
aihub/models/document_metadata_response.py
aihub/models/document_upload_response.py
aihub/models/document_upload_response_upload_status.py
aihub/models/document_upload_response_upload_status_failure_inner.py
aihub/models/document_upload_response_upload_status_success_inner.py
aihub/models/document_validations.py
aihub/models/error.py
instabase_aihub-0.13.0.dist-info/LICENSE
instabase_aihub-0.13.0.dist-info/METADATA
instabase_aihub-0.13.0.dist-info/WHEEL
instabase_aihub-0.13.0.dist-info/top_level.txt
instabase_aihub-0.13.0.dist-info/RECORD
