Metadata-Version: 2.1
Name: instabase-aihub
Version: 0.13.0
Summary: AI Hub API
Home-page: https://docs.instabase.com
Author: Instabase Support
Author-email: Instabase Support <support@instabase.com>
License: The MIT License
Project-URL: Repository, https://github.com/GIT_USER_ID/GIT_REPO_ID
Keywords: OpenAPI,OpenAPI-Generator,AI Hub API
Requires-Python: >=3.9
License-File: LICENSE
Requires-Dist: urllib3 <3.0.0,>=2.1.0
Requires-Dist: python-dateutil >=2.8.2
Requires-Dist: pydantic >=2
Requires-Dist: typing-extensions >=4.7.1
